{
    "keep": {
        "days": true,
        "amount": 1
    },
    "auditLog": "/app/config/logs/.20136e5b8544ec13f7fc29ce3d35150d597108bb-audit.json",
    "files": [
        {
            "date": 1762556467932,
            "name": "/app/config/logs/.machinelogs-2025-11-08.json",
            "hash": "888131e1354d498d22df828b9887d2e268fdafe245bc42b7f9ba2a2927a03d15"
        },
        {
            "date": 1762642803819,
            "name": "/app/config/logs/.machinelogs-2025-11-09.json",
            "hash": "44827f3fdfe82e39410711a73d4fdc4502d7c7c481eaae39f2ba1114337eacfa"
        }
    ],
    "hashType": "sha256"
}